{
  "서울특별시": {
    "강남구": {
      "보통교과": 1554,
      "외국어": 204,
      "기예(중)": 115,
      "기타(중)": 99,
      "예능(중)": 482,
      "산업응용기술": 65,
      "독서": 69,
      "국제": 42,
      "간호보조기술": 2,
      "일반서비스": 6,
      "진학지도": 71,
      "인문사회(중)": 20,
      "컴퓨터": 20,
      "경영·사무관리": 10,
      "산업서비스": 5,
      "문화관광": 4,
      "예능(대)": 2,
      "정보": 2,
      "산업기반기술": 2,
      "국제화": 1,
      "입시.검정 및 보습": 3
    },
    "강동구": {
      "예능(중)": 328,
      "간호보조기술": 3,
      "외국어": 57,
      "보통교과": 720,
      "기예(중)": 20,
      "산업기반기술": 3,
      "기타(중)": 36,
      "산업응용기술": 7,
      "독서": 18,
      "산업서비스": 1,
      "예능(대)": 4,
      "진학지도": 1,
      "정보": 1,
      "일반서비스": 2,
      "컴퓨터": 1,
      "국제": 1
    },
    "강북구": {
      "보통교과": 201,
      "외국어": 5,
      "일반서비스": 2,
      "예능(중)": 109,
      "기예(중)": 10,
      "산업응용기술": 3,
      "독서": 2,
      "기타(중)": 6,
      "산업기반기술": 2,
      "간호보조기술": 2,
      "정보": 1
    },
    "강서구": {
      "보통교과": 704,
      "예능(중)": 344,
      "기예(중)": 21,
      "산업응용기술": 7,
      "간호보조기술": 4,
      "산업서비스": 1,
      "외국어": 43,
      "독서": 17,
      "진학지도": 1,
      "기타(중)": 34,
      "경영·사무관리": 1,
      "산업기반기술": 2,
      "국제": 3,
      "입시.검정 및 보습": 1,
      "문화관광": 1,
      "예능(대)": 1,
      "인문사회(중)": 2,
      "일반서비스": 1
    },
    "관악구": {
      "독서": 31,
      "기예(중)": 30,
      "인문사회(중)": 23,
      "예능(중)": 205,
      "컴퓨터": 3,
      "보통교과": 305,
      "외국어": 16,
      "산업응용기술": 8,
      "기타(중)": 12,
      "간호보조기술": 3,
      "국제": 2,
      "산업기반기술": 1,
      "산업서비스": 2,
      "일반서비스": 2
    },
    "광진구": {
      "외국어": 21,
      "보통교과": 357,
      "예능(중)": 193,
      "독서": 14,
      "기타(중)": 20,
      "기예(중)": 24,
      "산업응용기술": 7,
      "간호보조기술": 2,
      "정보": 3,
      "컴퓨터": 2,
      "국제": 7,
      "산업기반기술": 4,
      "일반서비스": 2
    },
    "구로구": {
      "예능(중)": 237,
      "보통교과": 394,
      "컴퓨터": 11,
      "독서": 7,
      "기타(중)": 15,
      "국제": 2,
      "예능(대)": 2,
      "외국어": 18,
      "산업기반기술": 6,
      "기예(중)": 6,
      "산업응용기술": 5,
      "산업서비스": 1,
      "진학지도": 1,
      "일반서비스": 2,
      "정보": 1,
      "인문사회(중)": 1
    },
    "금천구": {
      "컴퓨터": 6,
      "보통교과": 157,
      "예능(중)": 106,
      "기타(중)": 7,
      "국제": 1,
      "인문사회(중)": 2,
      "간호보조기술": 1,
      "외국어": 8,
      "산업기반기술": 6,
      "독서": 3,
      "경영·사무관리": 3,
      "기예(중)": 7,
      "산업응용기술": 3,
      "산업서비스": 2
    },
    "노원구": {
      "독서": 30,
      "보통교과": 818,
      "외국어": 42,
      "예능(중)": 339,
      "기예(중)": 12,
      "기타(중)": 27,
      "컴퓨터": 5,
      "산업기반기술": 2,
      "인문사회(중)": 9,
      "일반서비스": 2,
      "경영·사무관리": 2,
      "산업응용기술": 9,
      "국제": 3,
      "입시.검정 및 보습": 1,
      "진학지도": 4,
      "간호보조기술": 3,
      "예능(대)": 2,
      "정보": 1,
      "직업기술": 1
    },
    "도봉구": {
      "보통교과": 335,
      "예능(중)": 156,
      "경영·사무관리": 2,
      "기타(중)": 16,
      "산업응용기술": 2,
      "일반서비스": 1,
      "기예(중)": 2,
      "외국어": 18,
      "간호보조기술": 3,
      "입시.검정 및 보습": 1,
      "독서": 10,
      "인문사회(중)": 2,
      "산업서비스": 1
    },
    "동대문구": {
      "보통교과": 340,
      "기예(중)": 17,
      "예능(중)": 183,
      "외국어": 36,
      "기타(중)": 11,
      "산업기반기술": 6,
      "산업응용기술": 10,
      "입시.검정 및 보습": 2,
      "독서": 6,
      "예능(대)": 1,
      "인문사회(중)": 1,
      "국제": 2,
      "간호보조기술": 2,
      "산업서비스": 1,
      "컴퓨터": 1,
      "경영·사무관리": 1,
      "일반서비스": 1,
      "진학지도": 1
    },
    "동작구": {
      "독서": 24,
      "보통교과": 398,
      "외국어": 52,
      "인문사회(중)": 55,
      "예능(중)": 194,
      "국제": 2,
      "기예(중)": 25,
      "기타(중)": 21,
      "산업기반기술": 7,
      "산업응용기술": 4,
      "간호보조기술": 1,
      "산업서비스": 2,
      "컴퓨터": 4,
      "경영·사무관리": 1,
      "일반서비스": 1,
      "예능(대)": 1,
      "진학지도": 1
    },
    "마포구": {
      "보통교과": 437,
      "예능(중)": 292,
      "외국어": 48,
      "국제": 14,
      "기타(중)": 33,
      "간호보조기술": 2,
      "기예(중)": 76,
      "독서": 9,
      "인문사회(중)": 7,
      "산업응용기술": 27,
      "컴퓨터": 11,
      "일반서비스": 4,
      "문화관광": 2,
      "정보": 1,
      "진학지도": 3,
      "산업서비스": 1,
      "산업기반기술": 1
    },
    "서대문구": {
      "보통교과": 345,
      "문화관광": 3,
      "예능(중)": 188,
      "기타(중)": 16,
      "외국어": 21,
      "컴퓨터": 1,
      "인문사회(중)": 9,
      "산업응용기술": 5,
      "기예(중)": 15,
      "산업기반기술": 1,
      "독서": 10,
      "일반서비스": 1,
      "국제": 4,
      "진학지도": 1,
      "간호보조기술": 1
    },
    "서초구": {
      "산업응용기술": 25,
      "외국어": 82,
      "보통교과": 745,
      "예능(중)": 345,
      "기예(중)": 65,
      "국제": 27,
      "기타(중)": 63,
      "진학지도": 12,
      "경영·사무관리": 13,
      "인문사회(중)": 29,
      "독서": 14,
      "산업기반기술": 6,
      "컴퓨터": 17,
      "산업서비스": 3,
      "문화관광": 2,
      "간호보조기술": 2,
      "일반서비스": 3,
      "정보": 1
    },
    "성동구": {
      "보통교과": 230,
      "외국어": 29,
      "예능(중)": 168,
      "기타(중)": 16,
      "산업기반기술": 2,
      "컴퓨터": 2,
      "기예(중)": 19,
      "산업응용기술": 3,
      "문화관광": 2,
      "국제": 3,
      "독서": 6,
      "인문사회(중)": 1,
      "경영·사무관리": 1,
      "일반서비스": 1
    },
    "성북구": {
      "보통교과": 522,
      "기예(중)": 13,
      "외국어": 28,
      "산업응용기술": 4,
      "예능(중)": 249,
      "독서": 13,
      "기타(중)": 14,
      "기타(대)": 1,
      "간호보조기술": 3,
      "예능(대)": 2,
      "컴퓨터": 1,
      "경영·사무관리": 1
    },
    "송파구": {
      "외국어": 91,
      "기타(중)": 65,
      "산업서비스": 4,
      "보통교과": 925,
      "예능(중)": 485,
      "국제": 4,
      "독서": 34,
      "간호보조기술": 4,
      "컴퓨터": 5,
      "예능(대)": 3,
      "경영·사무관리": 4,
      "산업기반기술": 6,
      "인문사회(중)": 5,
      "산업응용기술": 14,
      "진학지도": 4,
      "기예(중)": 39,
      "일반서비스": 1,
      "문화관광": 2
    },
    "양천구": {
      "외국어": 69,
      "보통교과": 1210,
      "기타(중)": 41,
      "예능(중)": 390,
      "독서": 42,
      "진학지도": 10,
      "기예(중)": 10,
      "국제": 2,
      "산업응용기술": 3,
      "일반서비스": 1,
      "정보": 1,
      "경영·사무관리": 1,
      "간호보조기술": 1,
      "컴퓨터": 1
    },
    "영등포구": {
      "보통교과": 341,
      "예능(중)": 234,
      "기예(중)": 37,
      "진학지도": 3,
      "외국어": 35,
      "일반서비스": 1,
      "독서": 6,
      "기타(중)": 16,
      "예능(대)": 1,
      "산업응용기술": 16,
      "인문사회(중)": 8,
      "산업기반기술": 14,
      "컴퓨터": 4,
      "산업서비스": 2,
      "경영·사무관리": 5,
      "기예(대)": 1,
      "국제": 4,
      "간호보조기술": 2,
      "문화관광": 2,
      "특수교육(중)": 1
    },
    "용산구": {
      "기예(중)": 7,
      "예능(중)": 77,
      "보통교과": 100,
      "외국어": 18,
      "산업응용기술": 4,
      "간호보조기술": 1,
      "국제화": 1,
      "정보": 1,
      "기타(중)": 6,
      "인문사회(중)": 1,
      "국제": 1,
      "산업서비스": 1,
      "컴퓨터": 1,
      "독서": 1,
      "진학지도": 1
    },
    "은평구": {
      "보통교과": 560,
      "외국어": 31,
      "산업응용기술": 7,
      "예능(중)": 277,
      "경영·사무관리": 2,
      "인문사회(중)": 2,
      "기예(중)": 12,
      "독서": 22,
      "기타(중)": 11,
      "산업서비스": 2,
      "간호보조기술": 4,
      "일반서비스": 1,
      "컴퓨터": 3,
      "정보": 2
    },
    "종로구": {
      "보통교과": 93,
      "국제": 19,
      "기타(중)": 9,
      "예능(중)": 53,
      "독서": 5,
      "기예(중)": 25,
      "인문사회(중)": 15,
      "산업기반기술": 7,
      "산업응용기술": 11,
      "국제화": 1,
      "외국어": 8,
      "문화관광": 2,
      "일반서비스": 1,
      "간호보조기술": 1,
      "컴퓨터": 1
    },
    "중구": {
      "보통교과": 47,
      "외국어": 13,
      "산업응용기술": 8,
      "기타(중)": 4,
      "예능(중)": 38,
      "기예(중)": 12,
      "국제": 9,
      "인문사회(중)": 3,
      "문화관광": 2,
      "입시.검정 및 보습": 1,
      "간호보조기술": 1,
      "독서": 2,
      "진학지도": 1,
      "산업기반기술": 1
    },
    "중랑구": {
      "보통교과": 259,
      "예능(중)": 160,
      "외국어": 18,
      "기예(중)": 10,
      "간호보조기술": 2,
      "산업응용기술": 6,
      "독서": 6,
      "예능(대)": 2,
      "컴퓨터": 3,
      "기타(중)": 14,
      "정보": 1,
      "산업기반기술": 2,
      "일반서비스": 2
    }
  },
  "부산광역시": {
    "강서구": {
      "보통교과": 259,
      "외국어": 71,
      "예능(중)": 140,
      "독서": 3,
      "기타(중)": 27,
      "기예(중)": 6,
      "컴퓨터": 3,
      "간호보조기술": 1,
      "산업응용기술": 4,
      "산업기반기술": 2,
      "인문사회(중)": 1,
      "국제": 1,
      "경영·사무관리": 1
    },
    "금정구": {
      "기예(중)": 15,
      "보통교과": 295,
      "외국어": 48,
      "산업응용기술": 7,
      "예능(중)": 140,
      "기타(중)": 18,
      "간호보조기술": 2,
      "산업기반기술": 2,
      "국제": 9,
      "컴퓨터": 2,
      "산업서비스": 2,
      "예능(대)": 1,
      "독서": 16,
      "인문사회(중)": 3
    },
    "기장군": {
      "보통교과": 259,
      "예능(중)": 114,
      "외국어": 65,
      "간호보조기술": 3,
      "기예(중)": 5,
      "산업응용기술": 4,
      "기타(중)": 17,
      "독서": 4,
      "산업기반기술": 2,
      "예능(대)": 1
    },
    "남구": {
      "국제": 7,
      "보통교과": 264,
      "외국어": 54,
      "예능(중)": 139,
      "기예(중)": 12,
      "기타(중)": 21,
      "간호보조기술": 2,
      "컴퓨터": 4,
      "독서": 9,
      "산업서비스": 1,
      "산업기반기술": 2,
      "일반서비스": 2,
      "산업응용기술": 4,
      "인문사회(중)": 1
    },
    "동구": {
      "보통교과": 52,
      "기타(중)": 3,
      "인문사회(중)": 2,
      "예능(중)": 22,
      "독서": 1,
      "산업기반기술": 3,
      "외국어": 4,
      "산업응용기술": 5,
      "기예(중)": 5,
      "컴퓨터": 1
    },
    "동래구": {
      "외국어": 91,
      "보통교과": 574,
      "산업응용기술": 12,
      "예능(중)": 219,
      "기예(중)": 16,
      "독서": 15,
      "기타(중)": 34,
      "예능(대)": 2,
      "컴퓨터": 3,
      "산업서비스": 1,
      "간호보조기술": 2,
      "경영·사무관리": 1,
      "진학지도": 1,
      "국제": 1,
      "산업기반기술": 3,
      "일반서비스": 2,
      "특수교육(중)": 1
    },
    "부산진구": {
      "산업서비스": 2,
      "보통교과": 307,
      "외국어": 65,
      "기예(중)": 45,
      "경영·사무관리": 5,
      "예능(중)": 155,
      "산업기반기술": 9,
      "국제": 20,
      "독서": 11,
      "산업응용기술": 34,
      "기타(중)": 31,
      "인문사회(중)": 6,
      "컴퓨터": 10,
      "일반서비스": 8,
      "간호보조기술": 6
    },
    "북구": {
      "보통교과": 330,
      "외국어": 49,
      "독서": 15,
      "예능(중)": 130,
      "산업기반기술": 5,
      "일반서비스": 2,
      "기타(중)": 26,
      "간호보조기술": 3,
      "산업서비스": 2,
      "기예(중)": 5,
      "경영·사무관리": 1,
      "산업응용기술": 2,
      "컴퓨터": 1,
      "인문사회(중)": 1
    },
    "사상구": {
      "보통교과": 143,
      "외국어": 15,
      "예능(중)": 63,
      "산업응용기술": 3,
      "일반서비스": 1,
      "기예(중)": 9,
      "산업기반기술": 2,
      "기타(중)": 2,
      "독서": 5,
      "산업서비스": 1,
      "간호보조기술": 1
    },
    "사하구": {
      "보통교과": 212,
      "예능(중)": 102,
      "기예(중)": 4,
      "독서": 3,
      "산업응용기술": 6,
      "외국어": 26,
      "컴퓨터": 3,
      "간호보조기술": 3,
      "기타(중)": 8,
      "진학지도": 1,
      "국제": 1
    },
    "서구": {
      "보통교과": 67,
      "예능(중)": 32,
      "외국어": 7,
      "기예(중)": 1,
      "기타(중)": 1,
      "독서": 1,
      "간호보조기술": 1
    },
    "수영구": {
      "보통교과": 228,
      "예능(중)": 109,
      "진학지도": 2,
      "외국어": 32,
      "기예(중)": 12,
      "기타(중)": 24,
      "산업응용기술": 5,
      "입시.검정 및 보습": 1,
      "독서": 9,
      "일반서비스": 1,
      "간호보조기술": 1,
      "산업기반기술": 1,
      "컴퓨터": 1,
      "국제": 1,
      "문화관광": 1
    },
    "연제구": {
      "예능(중)": 125,
      "외국어": 38,
      "보통교과": 277,
      "기예(중)": 11,
      "산업응용기술": 4,
      "일반서비스": 2,
      "산업기반기술": 2,
      "기타(중)": 17,
      "독서": 9,
      "간호보조기술": 2,
      "경영·사무관리": 1,
      "입시.검정 및 보습": 1
    },
    "영도구": {
      "예능(중)": 27,
      "보통교과": 41,
      "기예(중)": 1,
      "외국어": 2
    },
    "중구": {
      "보통교과": 7,
      "예능(중)": 6,
      "일반서비스": 1,
      "산업응용기술": 4,
      "기예(중)": 4,
      "산업기반기술": 2,
      "기타(중)": 1,
      "문화관광": 1
    },
    "해운대구": {
      "보통교과": 659,
      "컴퓨터": 3,
      "예능(중)": 265,
      "외국어": 153,
      "진학지도": 5,
      "기타(중)": 46,
      "예능(대)": 1,
      "독서": 16,
      "기예(중)": 11,
      "국제": 3,
      "산업응용기술": 9,
      "산업기반기술": 2,
      "산업서비스": 1,
      "일반서비스": 1,
      "인문사회(중)": 2,
      "간호보조기술": 3
    }
  },
  "대구광역시": {
    "군위군": {
      "보통교과": 6,
      "예능(중)": 6,
      "기타(중)": 1,
      "국제": 1
    },
    "남구": {
      "예능(중)": 82,
      "보통교과": 112,
      "산업기반기술": 4,
      "인문사회(중)": 1,
      "일반서비스": 2,
      "산업응용기술": 5,
      "기타(중)": 4,
      "독서": 2,
      "외국어": 4,
      "기예(중)": 4,
      "입시.검정 및 보습": 1,
      "국제": 2,
      "경영·사무관리": 1,
      "산업서비스": 1
    },
    "달서구": {
      "보통교과": 972,
      "국제": 2,
      "예능(중)": 374,
      "기타(중)": 26,
      "산업응용기술": 12,
      "외국어": 86,
      "기예(중)": 10,
      "산업기반기술": 10,
      "간호보조기술": 9,
      "예능(대)": 3,
      "독서": 25,
      "일반서비스": 3,
      "컴퓨터": 9,
      "산업서비스": 4,
      "인문사회(중)": 1,
      "진학지도": 3,
      "경영·사무관리": 1
    },
    "달성군": {
      "외국어": 43,
      "보통교과": 397,
      "기예(중)": 4,
      "예능(중)": 141,
      "컴퓨터": 4,
      "예능(대)": 1,
      "독서": 14,
      "산업기반기술": 2,
      "기타(중)": 3,
      "진학지도": 1,
      "정보": 1,
      "산업응용기술": 1,
      "간호보조기술": 2
    },
    "동구": {
      "보통교과": 429,
      "외국어": 43,
      "예능(중)": 231,
      "기예(중)": 7,
      "독서": 11,
      "산업응용기술": 7,
      "산업기반기술": 6,
      "일반서비스": 3,
      "기타(중)": 11,
      "간호보조기술": 4,
      "입시.검정 및 보습": 2,
      "인문사회(중)": 1,
      "산업서비스": 1,
      "국제": 1,
      "컴퓨터": 1
    },
    "북구": {
      "보통교과": 671,
      "컴퓨터": 3,
      "예능(중)": 280,
      "외국어": 49,
      "간호보조기술": 6,
      "기타(중)": 17,
      "산업기반기술": 4,
      "독서": 15,
      "인문사회(중)": 2,
      "일반서비스": 2,
      "경영·사무관리": 1,
      "산업응용기술": 4,
      "진학지도": 3,
      "국제": 1,
      "예능(대)": 2,
      "기예(중)": 5
    },
    "서구": {
      "보통교과": 124,
      "예능(중)": 61,
      "컴퓨터": 2,
      "진학지도": 1,
      "산업응용기술": 4,
      "산업기반기술": 4,
      "기예(중)": 5,
      "기타(중)": 4,
      "외국어": 4,
      "예능(대)": 1,
      "간호보조기술": 2,
      "독서": 2
    },
    "수성구": {
      "외국어": 145,
      "보통교과": 1389,
      "예능(중)": 450,
      "산업응용기술": 16,
      "기타(중)": 33,
      "산업서비스": 1,
      "입시.검정 및 보습": 2,
      "국제": 2,
      "기예(중)": 18,
      "독서": 33,
      "진학지도": 4,
      "인문사회(중)": 3,
      "컴퓨터": 6,
      "경영·사무관리": 2,
      "산업기반기술": 3,
      "일반서비스": 2,
      "간호보조기술": 2
    },
    "중구": {
      "기타(중)": 15,
      "보통교과": 124,
      "일반서비스": 5,
      "산업응용기술": 32,
      "예능(중)": 106,
      "외국어": 15,
      "기예(중)": 14,
      "인문사회(중)": 12,
      "산업기반기술": 6,
      "간호보조기술": 5,
      "산업서비스": 2,
      "독서": 5,
      "국제": 10,
      "컴퓨터": 5,
      "예능(대)": 2,
      "경영·사무관리": 1
    }
  },
  "인천광역시": {
    "강화군": {
      "보통교과": 31,
      "예능(중)": 17,
      "기타(중)": 3,
      "기예(중)": 1,
      "외국어": 6
    },
    "계양구": {
      "보통교과": 247,
      "예능(중)": 120,
      "외국어": 11,
      "기타(중)": 11,
      "산업서비스": 4,
      "산업기반기술": 2,
      "간호보조기술": 2,
      "기예(중)": 7,
      "독서": 10,
      "인문사회(중)": 1,
      "산업응용기술": 2,
      "정보": 1
    },
    "남동구": {
      "보통교과": 603,
      "예능(중)": 293,
      "외국어": 43,
      "기타(중)": 41,
      "기예(중)": 16,
      "산업응용기술": 21,
      "산업기반기술": 4,
      "독서": 15,
      "간호보조기술": 3,
      "컴퓨터": 2,
      "인문사회(중)": 2,
      "일반서비스": 5,
      "국제": 1,
      "예능(대)": 1,
      "산업서비스": 2,
      "문화관광": 1,
      "입시.검정 및 보습": 1
    },
    "동구": {
      "보통교과": 37,
      "예능(중)": 19,
      "기타(중)": 3,
      "산업응용기술": 1,
      "외국어": 1
    },
    "미추홀구": {
      "보통교과": 306,
      "외국어": 26,
      "산업응용기술": 7,
      "산업서비스": 1,
      "기예(중)": 8,
      "예능(중)": 158,
      "산업기반기술": 6,
      "인문사회(중)": 4,
      "독서": 7,
      "기타(중)": 10,
      "국제": 4,
      "경영·사무관리": 1,
      "컴퓨터": 3,
      "간호보조기술": 3,
      "일반서비스": 1
    },
    "부평구": {
      "보통교과": 461,
      "예능(중)": 243,
      "기예(중)": 17,
      "기타(중)": 27,
      "외국어": 24,
      "산업기반기술": 7,
      "국제": 3,
      "컴퓨터": 6,
      "간호보조기술": 3,
      "산업응용기술": 17,
      "산업서비스": 4,
      "인문사회(중)": 6,
      "독서": 14,
      "일반서비스": 2,
      "정보": 1
    },
    "서구": {
      "보통교과": 885,
      "기타(중)": 37,
      "외국어": 57,
      "기예(중)": 14,
      "예능(중)": 382,
      "산업서비스": 1,
      "간호보조기술": 4,
      "예능(대)": 3,
      "인문사회(중)": 1,
      "독서": 10,
      "정보": 1,
      "산업기반기술": 7,
      "산업응용기술": 2,
      "진학지도": 1
    },
    "연수구": {
      "보통교과": 751,
      "예능(중)": 313,
      "기타(중)": 48,
      "외국어": 82,
      "기예(중)": 11,
      "진학지도": 6,
      "독서": 17,
      "산업응용기술": 5,
      "문화관광": 1,
      "컴퓨터": 2,
      "국제": 2,
      "입시.검정 및 보습": 1,
      "간호보조기술": 2
    },
    "옹진군": {
      "예능(중)": 3
    },
    "중구": {
      "외국어": 17,
      "보통교과": 164,
      "기예(중)": 3,
      "예능(중)": 68,
      "기타(중)": 11,
      "컴퓨터": 1,
      "산업응용기술": 5,
      "독서": 1,
      "산업기반기술": 1,
      "입시.검정 및 보습": 1
    }
  },
  "광주광역시": {
    "광산구": {
      "외국어": 31,
      "보통교과": 739,
      "예능(중)": 263,
      "산업응용기술": 13,
      "예능(대)": 5,
      "정보": 1,
      "독서": 22,
      "기예(중)": 9,
      "간호보조기술": 8,
      "산업기반기술": 5,
      "컴퓨터": 7,
      "입시.검정 및 보습": 2,
      "기타(중)": 18,
      "진학지도": 3,
      "경영·사무관리": 1,
      "일반서비스": 1,
      "국제": 2
    },
    "남구": {
      "보통교과": 510,
      "예능(중)": 178,
      "외국어": 26,
      "특수교육(중)": 3,
      "기예(중)": 15,
      "기타(중)": 11,
      "산업기반기술": 3,
      "일반서비스": 2,
      "독서": 16,
      "산업서비스": 1,
      "입시.검정 및 보습": 2,
      "진학지도": 6,
      "간호보조기술": 5,
      "산업응용기술": 5,
      "컴퓨터": 2
    },
    "동구": {
      "보통교과": 148,
      "기예(중)": 27,
      "산업응용기술": 18,
      "독서": 9,
      "기타(중)": 12,
      "국제": 9,
      "예능(중)": 90,
      "컴퓨터": 4,
      "인문사회(중)": 5,
      "진학지도": 1,
      "산업기반기술": 9,
      "산업서비스": 2,
      "외국어": 7,
      "일반서비스": 3,
      "간호보조기술": 1,
      "경영·사무관리": 1
    },
    "북구": {
      "기예(중)": 38,
      "보통교과": 674,
      "독서": 36,
      "기타(중)": 22,
      "예능(중)": 286,
      "산업기반기술": 14,
      "외국어": 24,
      "국제": 7,
      "경영·사무관리": 3,
      "인문사회(중)": 6,
      "일반서비스": 2,
      "컴퓨터": 5,
      "산업응용기술": 16,
      "간호보조기술": 6,
      "예능(대)": 1,
      "입시.검정 및 보습": 2,
      "산업서비스": 1,
      "특수교육(중)": 1
    },
    "서구": {
      "보통교과": 489,
      "기예(중)": 20,
      "예능(중)": 197,
      "외국어": 25,
      "독서": 18,
      "산업응용기술": 11,
      "산업기반기술": 8,
      "간호보조기술": 4,
      "인문사회(중)": 1,
      "컴퓨터": 4,
      "특수교육(중)": 3,
      "기타(중)": 12,
      "경영·사무관리": 2,
      "일반서비스": 2,
      "산업서비스": 1,
      "국제": 2,
      "진학지도": 1
    }
  },
  "대전광역시": {
    "대덕구": {
      "보통교과": 178,
      "기예(중)": 8,
      "예능(중)": 78,
      "산업응용기술": 3,
      "독서": 7,
      "컴퓨터": 2,
      "기타(중)": 2,
      "외국어": 5,
      "산업기반기술": 1,
      "일반서비스": 1
    },
    "동구": {
      "보통교과": 165,
      "컴퓨터": 3,
      "산업응용기술": 6,
      "외국어": 6,
      "독서": 6,
      "예능(중)": 114,
      "기예(중)": 9,
      "간호보조기술": 1,
      "기타(중)": 3,
      "산업기반기술": 9,
      "인문사회(중)": 1,
      "경영·사무관리": 1,
      "국제": 1,
      "예능(대)": 1
    },
    "서구": {
      "보통교과": 707,
      "간호보조기술": 4,
      "독서": 29,
      "외국어": 61,
      "컴퓨터": 9,
      "산업응용기술": 25,
      "기타(중)": 49,
      "예능(중)": 326,
      "국제": 12,
      "기예(중)": 25,
      "인문사회(중)": 6,
      "산업기반기술": 7,
      "일반서비스": 2,
      "진학지도": 3,
      "경영·사무관리": 1,
      "산업서비스": 1
    },
    "유성구": {
      "외국어": 43,
      "보통교과": 509,
      "기타(중)": 28,
      "예능(중)": 311,
      "국제": 5,
      "산업응용기술": 2,
      "독서": 15,
      "기예(중)": 16,
      "인문사회(중)": 3,
      "산업기반기술": 7,
      "컴퓨터": 4,
      "경영·사무관리": 3,
      "간호보조기술": 3,
      "일반서비스": 2,
      "산업서비스": 1
    },
    "중구": {
      "산업응용기술": 15,
      "보통교과": 200,
      "컴퓨터": 5,
      "외국어": 19,
      "인문사회(중)": 5,
      "예능(중)": 118,
      "산업기반기술": 11,
      "기예(중)": 26,
      "일반서비스": 3,
      "기타(중)": 9,
      "독서": 11,
      "산업서비스": 2,
      "국제": 1,
      "정보": 1,
      "간호보조기술": 2
    }
  },
  "울산광역시": {
    "남구": {
      "예능(중)": 278,
      "보통교과": 626,
      "기예(중)": 22,
      "외국어": 123,
      "독서": 31,
      "컴퓨터": 6,
      "기타(중)": 33,
      "간호보조기술": 3,
      "산업기반기술": 6,
      "일반서비스": 8,
      "국제": 11,
      "산업응용기술": 21,
      "인문사회(중)": 2,
      "산업서비스": 2,
      "문화관광": 1,
      "진학지도": 2,
      "경영·사무관리": 3,
      "정보": 2
    },
    "동구": {
      "보통교과": 207,
      "독서": 10,
      "컴퓨터": 1,
      "외국어": 28,
      "예능(중)": 90,
      "기타(중)": 5,
      "기예(중)": 2,
      "산업기반기술": 2,
      "간호보조기술": 1,
      "예능(대)": 1,
      "산업응용기술": 4
    },
    "북구": {
      "예능(중)": 159,
      "보통교과": 390,
      "외국어": 68,
      "독서": 11,
      "기예(중)": 5,
      "일반서비스": 1,
      "산업기반기술": 4,
      "산업응용기술": 7,
      "간호보조기술": 2,
      "기타(중)": 3,
      "정보": 2,
      "컴퓨터": 2
    },
    "울주군": {
      "보통교과": 289,
      "예능(중)": 129,
      "외국어": 53,
      "독서": 15,
      "기타(중)": 10,
      "기예(중)": 2,
      "입시.검정 및 보습": 1,
      "일반서비스": 1,
      "컴퓨터": 1,
      "산업응용기술": 5,
      "산업기반기술": 3
    },
    "중구": {
      "보통교과": 278,
      "외국어": 46,
      "예능(중)": 146,
      "컴퓨터": 5,
      "독서": 10,
      "산업응용기술": 15,
      "기예(중)": 13,
      "간호보조기술": 2,
      "국제": 1,
      "기타(중)": 8,
      "예능(대)": 1,
      "진학지도": 2,
      "산업기반기술": 2,
      "산업서비스": 2,
      "인문사회(중)": 2,
      "경영·사무관리": 1,
      "일반서비스": 1
    }
  },
  "세종특별자치시": {
    "세종특별자치시": {
      "보통교과": 730,
      "외국어": 177,
      "예능(중)": 399,
      "기타(중)": 28,
      "독서": 13,
      "기예(중)": 17,
      "산업응용기술": 12,
      "입시.검정 및 보습": 2,
      "국제": 3,
      "산업기반기술": 3,
      "컴퓨터": 3,
      "경영·사무관리": 3,
      "정보": 5,
      "예능(대)": 3,
      "간호보조기술": 5,
      "인문사회(중)": 3,
      "일반서비스": 3,
      "진학지도": 3
    }
  },
  "경기도": {
    "가평군": {
      "보통교과": 38,
      "외국어": 2,
      "예능(중)": 31,
      "기타(중)": 2
    },
    "고양시": {
      "예능(중)": 823,
      "보통교과": 1736,
      "외국어": 169,
      "기타(중)": 87,
      "컴퓨터": 7,
      "진학지도": 2,
      "산업응용기술": 19,
      "기예(중)": 16,
      "독서": 57,
      "국제": 13,
      "인문사회(중)": 3,
      "간호보조기술": 9,
      "경영·사무관리": 4,
      "일반서비스": 8,
      "정보": 8,
      "산업기반기술": 8,
      "산업서비스": 3
    },
    "과천시": {
      "보통교과": 90,
      "예능(중)": 40,
      "외국어": 12,
      "정보": 2,
      "기타(중)": 3
    },
    "광명시": {
      "예능(중)": 203,
      "보통교과": 481,
      "외국어": 44,
      "산업응용기술": 6,
      "기예(중)": 15,
      "일반서비스": 1,
      "산업기반기술": 1,
      "간호보조기술": 2,
      "독서": 11,
      "기타(중)": 15,
      "컴퓨터": 1,
      "정보": 2,
      "국제": 1
    },
    "광주시": {
      "보통교과": 402,
      "외국어": 32,
      "예능(중)": 214,
      "간호보조기술": 1,
      "산업기반기술": 2,
      "예능(대)": 1,
      "기타(중)": 13,
      "컴퓨터": 1,
      "독서": 6,
      "기예(중)": 8,
      "산업응용기술": 2,
      "산업서비스": 1,
      "인문사회(중)": 1,
      "일반서비스": 1,
      "정보": 1
    },
    "구리시": {
      "보통교과": 314,
      "예능(중)": 137,
      "외국어": 21,
      "기타(중)": 16,
      "산업응용기술": 7,
      "간호보조기술": 2,
      "일반서비스": 3,
      "기예(중)": 1,
      "독서": 7,
      "입시.검정 및 보습": 2,
      "컴퓨터": 1,
      "인문사회(중)": 1
    },
    "군포시": {
      "보통교과": 355,
      "예능(중)": 181,
      "기타(중)": 19,
      "국제": 4,
      "기예(중)": 10,
      "산업응용기술": 3,
      "간호보조기술": 2,
      "외국어": 18,
      "입시.검정 및 보습": 1,
      "독서": 8,
      "산업기반기술": 2,
      "예능(대)": 2,
      "컴퓨터": 1,
      "진학지도": 1
    },
    "김포시": {
      "보통교과": 870,
      "예능(중)": 388,
      "외국어": 103,
      "기타(중)": 50,
      "컴퓨터": 3,
      "산업응용기술": 14,
      "독서": 19,
      "일반서비스": 4,
      "예능(대)": 4,
      "기예(중)": 9,
      "간호보조기술": 4,
      "경영·사무관리": 1,
      "산업기반기술": 7,
      "입시.검정 및 보습": 1,
      "진학지도": 1,
      "정보": 1,
      "문화관광": 1
    },
    "남양주시": {
      "보통교과": 1037,
      "기예(중)": 11,
      "외국어": 79,
      "예능(중)": 474,
      "산업응용기술": 9,
      "기타(중)": 46,
      "독서": 21,
      "산업기반기술": 5,
      "간호보조기술": 6,
      "일반서비스": 2,
      "컴퓨터": 1,
      "정보": 5,
      "예능(대)": 1,
      "입시.검정 및 보습": 1,
      "산업서비스": 1
    },
    "동두천시": {
      "외국어": 5,
      "보통교과": 53,
      "예능(중)": 34,
      "독서": 3,
      "간호보조기술": 1,
      "산업기반기술": 2,
      "기타(중)": 2,
      "컴퓨터": 1
    },
    "부천시": {
      "예능(중)": 549,
      "보통교과": 964,
      "외국어": 83,
      "독서": 30,
      "기예(중)": 19,
      "기타(중)": 67,
      "산업서비스": 3,
      "국제": 6,
      "산업기반기술": 11,
      "경영·사무관리": 2,
      "컴퓨터": 4,
      "예능(대)": 3,
      "간호보조기술": 6,
      "산업응용기술": 15,
      "인문사회(중)": 2,
      "일반서비스": 4,
      "진학지도": 3
    },
    "성남시": {
      "보통교과": 1790,
      "입시.검정 및 보습": 4,
      "독서": 79,
      "예능(중)": 866,
      "외국어": 184,
      "기타(중)": 87,
      "진학지도": 17,
      "산업응용기술": 28,
      "산업기반기술": 10,
      "기예(중)": 39,
      "일반서비스": 9,
      "예능(대)": 4,
      "인문사회(중)": 3,
      "산업서비스": 4,
      "정보": 1,
      "국제": 12,
      "경영·사무관리": 5,
      "간호보조기술": 7,
      "컴퓨터": 4
    },
    "수원시": {
      "예능(중)": 888,
      "보통교과": 1644,
      "외국어": 164,
      "정보": 6,
      "독서": 57,
      "기타(중)": 102,
      "산업기반기술": 19,
      "인문사회(중)": 13,
      "산업응용기술": 31,
      "기예(중)": 37,
      "일반서비스": 6,
      "컴퓨터": 7,
      "국제": 14,
      "경영·사무관리": 8,
      "산업서비스": 2,
      "간호보조기술": 12,
      "진학지도": 3
    },
    "시흥시": {
      "보통교과": 759,
      "외국어": 56,
      "예능(중)": 367,
      "정보": 3,
      "산업기반기술": 6,
      "간호보조기술": 4,
      "기예(중)": 5,
      "기타(중)": 18,
      "독서": 13,
      "예능(대)": 6,
      "진학지도": 3,
      "컴퓨터": 5,
      "국제": 2,
      "일반서비스": 1,
      "경영·사무관리": 1,
      "산업응용기술": 3,
      "입시.검정 및 보습": 1
    },
    "안산시": {
      "보통교과": 580,
      "예능(중)": 306,
      "외국어": 36,
      "기타(중)": 17,
      "컴퓨터": 6,
      "산업기반기술": 11,
      "기예(중)": 19,
      "독서": 19,
      "국제": 4,
      "간호보조기술": 6,
      "산업응용기술": 15,
      "경영·사무관리": 2,
      "진학지도": 2,
      "일반서비스": 5,
      "산업서비스": 1
    },
    "안성시": {
      "보통교과": 167,
      "예능(중)": 91,
      "외국어": 16,
      "기타(중)": 6,
      "컴퓨터": 2,
      "독서": 7,
      "기예(중)": 6,
      "산업기반기술": 3,
      "국제": 1,
      "간호보조기술": 2,
      "산업응용기술": 3
    },
    "안양시": {
      "보통교과": 972,
      "기예(중)": 20,
      "예능(중)": 448,
      "외국어": 70,
      "산업응용기술": 15,
      "산업서비스": 2,
      "산업기반기술": 7,
      "기타(중)": 40,
      "독서": 24,
      "인문사회(중)": 4,
      "국제": 7,
      "일반서비스": 1,
      "정보": 2,
      "진학지도": 2,
      "간호보조기술": 6,
      "경영·사무관리": 1,
      "컴퓨터": 4,
      "문화관광": 1
    },
    "양주시": {
      "예능(중)": 140,
      "보통교과": 263,
      "외국어": 28,
      "산업기반기술": 7,
      "기예(중)": 3,
      "기타(중)": 8,
      "산업응용기술": 3,
      "산업서비스": 2,
      "일반서비스": 1,
      "간호보조기술": 2,
      "독서": 8,
      "진학지도": 1,
      "컴퓨터": 1
    },
    "양평군": {
      "보통교과": 117,
      "예능(중)": 54,
      "정보": 2,
      "외국어": 6,
      "산업응용기술": 3,
      "산업기반기술": 4,
      "예능(대)": 1,
      "기타(중)": 5,
      "컴퓨터": 1
    },
    "여주시": {
      "보통교과": 92,
      "예능(중)": 44,
      "외국어": 5,
      "기예(중)": 1,
      "산업응용기술": 1,
      "간호보조기술": 1,
      "기타(중)": 1,
      "산업기반기술": 1
    },
    "연천군": {
      "보통교과": 20,
      "예능(중)": 9,
      "외국어": 3,
      "기타(중)": 1
    },
    "오산시": {
      "보통교과": 244,
      "외국어": 25,
      "예능(중)": 139,
      "독서": 12,
      "일반서비스": 2,
      "입시.검정 및 보습": 1,
      "기타(중)": 5,
      "컴퓨터": 1,
      "기예(중)": 3,
      "산업응용기술": 2,
      "정보": 2,
      "간호보조기술": 2,
      "산업기반기술": 2
    },
    "용인시": {
      "산업기반기술": 5,
      "보통교과": 1623,
      "외국어": 179,
      "예능(중)": 906,
      "기예(중)": 18,
      "독서": 49,
      "기타(중)": 61,
      "간호보조기술": 7,
      "산업응용기술": 17,
      "인문사회(중)": 2,
      "일반서비스": 1,
      "컴퓨터": 5,
      "정보": 3,
      "예능(대)": 1,
      "산업서비스": 2,
      "문화관광": 1
    },
    "의왕시": {
      "보통교과": 167,
      "예능(중)": 92,
      "외국어": 12,
      "기타(중)": 2,
      "기예(중)": 4,
      "컴퓨터": 1,
      "예능(대)": 2,
      "산업응용기술": 2,
      "입시.검정 및 보습": 1,
      "독서": 4
    },
    "의정부시": {
      "보통교과": 556,
      "산업응용기술": 10,
      "외국어": 45,
      "예능(중)": 295,
      "간호보조기술": 5,
      "기타(중)": 36,
      "독서": 12,
      "산업기반기술": 2,
      "국제": 2,
      "일반서비스": 3,
      "기예(중)": 6,
      "컴퓨터": 1,
      "경영·사무관리": 1,
      "입시.검정 및 보습": 1,
      "예능(대)": 1,
      "정보": 1
    },
    "이천시": {
      "보통교과": 301,
      "산업응용기술": 6,
      "예능(중)": 123,
      "진학지도": 2,
      "외국어": 17,
      "독서": 11,
      "기타(중)": 8,
      "기예(중)": 8,
      "컴퓨터": 3,
      "간호보조기술": 1,
      "인문사회(중)": 1,
      "산업기반기술": 2
    },
    "파주시": {
      "산업기반기술": 5,
      "보통교과": 569,
      "기타(중)": 46,
      "외국어": 68,
      "산업응용기술": 8,
      "기예(중)": 12,
      "예능(중)": 282,
      "독서": 14,
      "일반서비스": 1,
      "간호보조기술": 4,
      "컴퓨터": 2,
      "경영·사무관리": 2,
      "인문사회(중)": 1,
      "입시.검정 및 보습": 1,
      "정보": 2
    },
    "평택시": {
      "보통교과": 587,
      "예능(중)": 352,
      "외국어": 70,
      "국제": 6,
      "산업응용기술": 23,
      "기타(중)": 24,
      "독서": 15,
      "산업기반기술": 12,
      "일반서비스": 6,
      "컴퓨터": 2,
      "기예(중)": 8,
      "간호보조기술": 4,
      "예능(대)": 1,
      "경영·사무관리": 1,
      "인문사회(중)": 1,
      "정보": 1,
      "산업서비스": 2
    },
    "포천시": {
      "산업응용기술": 3,
      "보통교과": 64,
      "외국어": 2,
      "예능(중)": 44,
      "기타(중)": 4,
      "기예(중)": 3,
      "산업기반기술": 4,
      "독서": 1,
      "간호보조기술": 1,
      "산업서비스": 2
    },
    "하남시": {
      "예능(중)": 244,
      "보통교과": 507,
      "외국어": 59,
      "기예(중)": 11,
      "기타(중)": 19,
      "진학지도": 4,
      "정보": 4,
      "독서": 9,
      "입시.검정 및 보습": 1,
      "산업서비스": 2,
      "산업응용기술": 7,
      "일반서비스": 2,
      "국제": 1,
      "산업기반기술": 2,
      "컴퓨터": 2,
      "간호보조기술": 2
    },
    "화성시": {
      "보통교과": 1635,
      "예능(중)": 765,
      "외국어": 195,
      "산업응용기술": 19,
      "독서": 25,
      "컴퓨터": 4,
      "산업기반기술": 12,
      "기타(중)": 85,
      "간호보조기술": 8,
      "기예(중)": 9,
      "경영·사무관리": 4,
      "일반서비스": 2,
      "인문사회(중)": 2,
      "정보": 8,
      "국제": 7,
      "산업서비스": 2,
      "예능(대)": 1,
      "진학지도": 1,
      "문화관광": 2
    }
  },
  "강원특별자치도": {
    "강릉시": {
      "보통교과": 257,
      "예능(중)": 123,
      "기타(중)": 9,
      "독서": 12,
      "외국어": 48,
      "산업응용기술": 11,
      "간호보조기술": 1,
      "인문사회(중)": 5,
      "기예(중)": 12,
      "일반서비스": 2,
      "산업기반기술": 7,
      "컴퓨터": 1,
      "예능(대)": 1
    },
    "고성군": {
      "산업기반기술": 2,
      "보통교과": 5,
      "외국어": 1,
      "예능(중)": 6
    },
    "동해시": {
      "외국어": 14,
      "보통교과": 79,
      "예능(중)": 43,
      "기타(중)": 2,
      "컴퓨터": 2,
      "독서": 6,
      "산업응용기술": 8,
      "간호보조기술": 2,
      "산업기반기술": 1,
      "기예(중)": 1,
      "경영·사무관리": 1
    },
    "삼척시": {
      "보통교과": 17,
      "외국어": 2,
      "예능(중)": 12,
      "기타(중)": 1,
      "산업응용기술": 1,
      "독서": 1
    },
    "속초시": {
      "보통교과": 73,
      "외국어": 5,
      "기예(중)": 2,
      "예능(중)": 40,
      "산업응용기술": 6,
      "독서": 8,
      "간호보조기술": 1,
      "산업기반기술": 1,
      "기타(중)": 2,
      "진학지도": 1,
      "일반서비스": 1
    },
    "양구군": {
      "산업기반기술": 1,
      "예능(중)": 7,
      "보통교과": 10,
      "기타(중)": 1
    },
    "양양군": {
      "보통교과": 19,
      "독서": 3,
      "예능(중)": 4,
      "일반서비스": 1
    },
    "영월군": {
      "보통교과": 23,
      "기타(중)": 5,
      "예능(중)": 10,
      "독서": 1,
      "외국어": 1
    },
    "원주시": {
      "간호보조기술": 4,
      "예능(중)": 219,
      "외국어": 58,
      "보통교과": 411,
      "기타(중)": 20,
      "기예(중)": 31,
      "산업응용기술": 20,
      "독서": 19,
      "인문사회(중)": 4,
      "산업기반기술": 10,
      "진학지도": 3,
      "컴퓨터": 4,
      "국제": 2,
      "특수교육(중)": 1,
      "일반서비스": 2
    },
    "인제군": {
      "보통교과": 15,
      "예능(중)": 16,
      "외국어": 2
    },
    "정선군": {
      "보통교과": 10,
      "기타(중)": 4,
      "예능(중)": 11,
      "외국어": 1
    },
    "철원군": {
      "보통교과": 22,
      "예능(중)": 11,
      "독서": 2,
      "산업기반기술": 1,
      "외국어": 1
    },
    "춘천시": {
      "보통교과": 321,
      "예능(중)": 182,
      "외국어": 38,
      "산업응용기술": 12,
      "간호보조기술": 2,
      "산업기반기술": 3,
      "기타(중)": 15,
      "기예(중)": 6,
      "독서": 16,
      "국제": 3,
      "일반서비스": 2,
      "인문사회(중)": 4,
      "예능(대)": 1,
      "입시.검정 및 보습": 1,
      "진학지도": 1,
      "산업서비스": 1,
      "컴퓨터": 2
    },
    "태백시": {
      "예능(중)": 14,
      "보통교과": 19,
      "외국어": 4,
      "독서": 1,
      "산업응용기술": 1,
      "기예(중)": 1,
      "산업기반기술": 1,
      "컴퓨터": 1
    },
    "평창군": {
      "보통교과": 19,
      "예능(중)": 6,
      "독서": 1,
      "외국어": 1
    },
    "홍천군": {
      "외국어": 5,
      "보통교과": 36,
      "예능(중)": 28,
      "입시.검정 및 보습": 2,
      "예능(대)": 1,
      "기예(중)": 1,
      "독서": 2,
      "컴퓨터": 1,
      "산업응용기술": 1
    },
    "화천군": {
      "보통교과": 18,
      "예능(중)": 5
    },
    "횡성군": {
      "보통교과": 26,
      "예능(중)": 9,
      "외국어": 1,
      "진학지도": 1,
      "간호보조기술": 1
    }
  },
  "충청북도": {
    "괴산군": {
      "보통교과": 7,
      "예능(중)": 5,
      "외국어": 2
    },
    "단양군": {
      "예능(중)": 8,
      "보통교과": 11,
      "산업응용기술": 1
    },
    "보은군": {
      "보통교과": 14,
      "외국어": 2,
      "산업응용기술": 1,
      "예능(중)": 5,
      "독서": 1,
      "컴퓨터": 1
    },
    "상당구": {
      "보통교과": 238,
      "산업응용기술": 14,
      "외국어": 47,
      "예능(중)": 151,
      "컴퓨터": 2,
      "기타(중)": 18,
      "입시.검정 및 보습": 1,
      "기예(중)": 6,
      "간호보조기술": 5,
      "독서": 10,
      "산업서비스": 2,
      "산업기반기술": 5,
      "경영·사무관리": 1,
      "정보": 1
    },
    "서원구": {
      "경영·사무관리": 1,
      "보통교과": 248,
      "기예(중)": 8,
      "예능(중)": 116,
      "외국어": 44,
      "기타(중)": 13,
      "산업응용기술": 9,
      "독서": 11,
      "일반서비스": 3,
      "인문사회(중)": 4,
      "컴퓨터": 2,
      "국제": 5,
      "산업기반기술": 2,
      "산업서비스": 1
    },
    "영동군": {
      "예능(중)": 16,
      "보통교과": 23,
      "독서": 3,
      "외국어": 4
    },
    "옥천군": {
      "보통교과": 22,
      "독서": 1,
      "예능(중)": 11,
      "산업응용기술": 2,
      "정보": 1
    },
    "음성군": {
      "보통교과": 41,
      "기예(중)": 3,
      "예능(중)": 30,
      "산업응용기술": 2,
      "간호보조기술": 2,
      "외국어": 2,
      "독서": 2,
      "기타(중)": 3,
      "산업기반기술": 2,
      "컴퓨터": 1
    },
    "제천시": {
      "예능(중)": 50,
      "외국어": 11,
      "산업응용기술": 6,
      "보통교과": 126,
      "기예(중)": 5,
      "간호보조기술": 2,
      "기타(중)": 6,
      "독서": 2,
      "인문사회(중)": 2,
      "입시.검정 및 보습": 1,
      "산업기반기술": 3
    },
    "증평군": {
      "보통교과": 31,
      "산업응용기술": 1,
      "예능(중)": 18,
      "컴퓨터": 1,
      "외국어": 7,
      "간호보조기술": 1
    },
    "진천군": {
      "예능(중)": 36,
      "산업응용기술": 3,
      "외국어": 6,
      "보통교과": 70,
      "산업기반기술": 2,
      "간호보조기술": 1,
      "기예(중)": 2,
      "독서": 1
    },
    "청원구": {
      "보통교과": 191,
      "외국어": 36,
      "독서": 6,
      "산업응용기술": 1,
      "예능(중)": 124,
      "간호보조기술": 1,
      "기예(중)": 8,
      "기타(중)": 9,
      "산업기반기술": 4,
      "일반서비스": 1,
      "국제": 1,
      "컴퓨터": 1,
      "정보": 1,
      "예능(대)": 1,
      "진학지도": 1
    },
    "청주시": {
      "보통교과": 4,
      "예능(중)": 1
    },
    "충주시": {
      "보통교과": 237,
      "예능(중)": 116,
      "외국어": 26,
      "기예(중)": 6,
      "기타(중)": 11,
      "간호보조기술": 3,
      "독서": 7,
      "일반서비스": 1,
      "컴퓨터": 3,
      "국제": 2,
      "산업응용기술": 9,
      "인문사회(중)": 2,
      "산업기반기술": 1
    },
    "흥덕구": {
      "보통교과": 357,
      "예능(중)": 205,
      "기타(중)": 35,
      "외국어": 90,
      "컴퓨터": 2,
      "독서": 11,
      "산업응용기술": 8,
      "기예(중)": 9,
      "산업기반기술": 5,
      "정보": 1,
      "경영·사무관리": 1,
      "인문사회(중)": 1,
      "간호보조기술": 2,
      "일반서비스": 1,
      "예능(대)": 1
    }
  },
  "충청남도": {
    "계룡시": {
      "보통교과": 55,
      "외국어": 10,
      "입시.검정 및 보습": 1,
      "인문사회(중)": 1,
      "예능(중)": 23,
      "독서": 4,
      "기타(중)": 1,
      "기예(중)": 1,
      "간호보조기술": 1
    },
    "공주시": {
      "보통교과": 71,
      "외국어": 9,
      "예능(중)": 27,
      "간호보조기술": 2,
      "산업응용기술": 3,
      "기예(중)": 3,
      "독서": 4,
      "산업기반기술": 1
    },
    "금산군": {
      "외국어": 2,
      "예능(중)": 11,
      "보통교과": 16,
      "기타(중)": 1,
      "산업기반기술": 1,
      "진학지도": 1,
      "기예(중)": 1,
      "간호보조기술": 1,
      "컴퓨터": 1
    },
    "논산시": {
      "예능(중)": 49,
      "외국어": 9,
      "보통교과": 57,
      "산업응용기술": 5,
      "간호보조기술": 2,
      "산업기반기술": 1,
      "컴퓨터": 3,
      "독서": 2,
      "기타(중)": 4,
      "기예(중)": 4,
      "경영·사무관리": 1
    },
    "당진시": {
      "보통교과": 126,
      "외국어": 26,
      "기예(중)": 2,
      "예능(중)": 88,
      "기타(중)": 3,
      "산업응용기술": 8,
      "기타(대)": 1,
      "독서": 3,
      "간호보조기술": 2,
      "일반서비스": 1,
      "산업기반기술": 4,
      "컴퓨터": 1,
      "예능(대)": 3,
      "입시.검정 및 보습": 1,
      "산업서비스": 1
    },
    "보령시": {
      "컴퓨터": 1,
      "보통교과": 56,
      "예능(중)": 38,
      "외국어": 18,
      "간호보조기술": 1,
      "산업응용기술": 1,
      "기타(중)": 5,
      "독서": 1
    },
    "부여군": {
      "보통교과": 21,
      "예능(중)": 12,
      "산업응용기술": 1,
      "기예(중)": 2,
      "독서": 3,
      "외국어": 4
    },
    "서산시": {
      "산업응용기술": 10,
      "보통교과": 128,
      "외국어": 34,
      "독서": 8,
      "예능(중)": 93,
      "입시.검정 및 보습": 2,
      "간호보조기술": 1,
      "기예(중)": 3,
      "인문사회(중)": 1,
      "일반서비스": 3,
      "산업기반기술": 1,
      "기타(중)": 2
    },
    "서천군": {
      "보통교과": 21,
      "외국어": 4,
      "예능(중)": 19,
      "독서": 4,
      "기예(중)": 3,
      "산업응용기술": 1
    },
    "아산시": {
      "예능(중)": 179,
      "보통교과": 266,
      "외국어": 68,
      "산업응용기술": 4,
      "기타(중)": 9,
      "기예(중)": 4,
      "정보": 5,
      "입시.검정 및 보습": 2,
      "간호보조기술": 2,
      "산업기반기술": 2,
      "예능(대)": 2,
      "독서": 1,
      "일반서비스": 1,
      "컴퓨터": 1,
      "국제": 1
    },
    "연기군": {
      "산업서비스": 1,
      "외국어": 11,
      "예능(중)": 42,
      "보통교과": 43,
      "기타(중)": 3,
      "컴퓨터": 1,
      "산업응용기술": 3,
      "간호보조기술": 1,
      "기예(중)": 2,
      "독서": 2
    },
    "예산군": {
      "보통교과": 26,
      "예능(중)": 18,
      "일반서비스": 1,
      "외국어": 3,
      "기타(중)": 1
    },
    "천안시": {
      "외국어": 178,
      "예능(중)": 429,
      "보통교과": 801,
      "기타(중)": 31,
      "컴퓨터": 8,
      "산업기반기술": 16,
      "기예(중)": 14,
      "산업응용기술": 27,
      "독서": 17,
      "진학지도": 5,
      "예능(대)": 1,
      "국제": 8,
      "일반서비스": 5,
      "인문사회(중)": 3,
      "간호보조기술": 8,
      "정보": 1,
      "경영·사무관리": 3,
      "산업서비스": 1
    },
    "청양군": {
      "보통교과": 2,
      "컴퓨터": 1,
      "예능(중)": 3,
      "기타(중)": 1
    },
    "태안군": {
      "보통교과": 20,
      "예능(중)": 16,
      "외국어": 9,
      "독서": 1,
      "산업응용기술": 2
    },
    "홍성군": {
      "보통교과": 65,
      "기타(중)": 4,
      "독서": 3,
      "예능(중)": 41,
      "간호보조기술": 2,
      "외국어": 15,
      "산업응용기술": 8,
      "기예(중)": 2
    }
  },
  "전북특별자치도": {
    "고창군": {
      "보통교과": 43,
      "독서": 2,
      "기예(중)": 1,
      "산업응용기술": 1,
      "간호보조기술": 1,
      "예능(중)": 14,
      "외국어": 4
    },
    "군산시": {
      "보통교과": 276,
      "외국어": 40,
      "예능(중)": 188,
      "산업응용기술": 13,
      "독서": 9,
      "기타(중)": 5,
      "인문사회(중)": 1,
      "경영·사무관리": 2,
      "간호보조기술": 3,
      "산업기반기술": 5,
      "기예(중)": 5,
      "예능(대)": 1,
      "컴퓨터": 4,
      "일반서비스": 1,
      "산업서비스": 1
    },
    "김제시": {
      "예능(중)": 31,
      "기예(중)": 4,
      "독서": 2,
      "보통교과": 38,
      "외국어": 8,
      "간호보조기술": 1,
      "산업응용기술": 3,
      "기타(중)": 1,
      "컴퓨터": 1,
      "일반서비스": 1
    },
    "남원시": {
      "보통교과": 59,
      "예능(중)": 36,
      "독서": 8,
      "간호보조기술": 1,
      "산업응용기술": 5,
      "기예(중)": 2,
      "컴퓨터": 2,
      "산업기반기술": 1,
      "기타(중)": 2,
      "외국어": 5
    },
    "무주군": {
      "외국어": 3,
      "예능(중)": 6,
      "보통교과": 14
    },
    "부안군": {
      "보통교과": 33,
      "예능(중)": 15,
      "기타(중)": 1,
      "독서": 1,
      "국제": 1,
      "산업기반기술": 1
    },
    "순창군": {
      "보통교과": 13,
      "예능(중)": 7,
      "기예(중)": 1
    },
    "완주군": {
      "보통교과": 91,
      "외국어": 16,
      "예능(중)": 47,
      "간호보조기술": 1,
      "국제": 1,
      "인문사회(중)": 1,
      "산업기반기술": 1,
      "독서": 1,
      "기예(중)": 1
    },
    "익산시": {
      "보통교과": 293,
      "외국어": 40,
      "산업응용기술": 13,
      "예능(중)": 142,
      "독서": 10,
      "입시.검정 및 보습": 1,
      "산업기반기술": 2,
      "기예(중)": 7,
      "기타(중)": 6,
      "컴퓨터": 5,
      "국제": 3,
      "예능(대)": 2,
      "간호보조기술": 2,
      "일반서비스": 2,
      "인문사회(중)": 2
    },
    "임실군": {
      "보통교과": 11,
      "예능(중)": 8,
      "기타(중)": 1
    },
    "장수군": {
      "보통교과": 14,
      "예능(중)": 5
    },
    "전주시": {
      "보통교과": 1110,
      "외국어": 221,
      "예능(중)": 583,
      "독서": 58,
      "산업기반기술": 14,
      "기예(중)": 60,
      "컴퓨터": 16,
      "산업응용기술": 30,
      "국제": 14,
      "기타(중)": 43,
      "입시.검정 및 보습": 2,
      "예능(대)": 3,
      "경영·사무관리": 3,
      "인문사회(중)": 8,
      "산업서비스": 7,
      "간호보조기술": 6,
      "진학지도": 1,
      "일반서비스": 3
    },
    "정읍시": {
      "보통교과": 94,
      "외국어": 7,
      "예능(중)": 69,
      "기예(중)": 6,
      "독서": 4,
      "컴퓨터": 4,
      "기타(중)": 6,
      "산업기반기술": 5,
      "간호보조기술": 1,
      "예능(대)": 1,
      "산업응용기술": 1,
      "정보": 1
    },
    "진안군": {
      "기예(중)": 1,
      "예능(중)": 3,
      "보통교과": 7,
      "외국어": 3
    }
  },
  "전라남도": {
    "강진군": {
      "외국어": 4,
      "예능(중)": 8,
      "보통교과": 14
    },
    "고흥군": {
      "외국어": 9,
      "예능(중)": 12,
      "보통교과": 19,
      "독서": 1,
      "산업응용기술": 1,
      "간호보조기술": 1
    },
    "곡성군": {
      "보통교과": 14,
      "예능(중)": 3,
      "외국어": 1
    },
    "광양시": {
      "예능(중)": 67,
      "보통교과": 131,
      "기타(중)": 5,
      "산업응용기술": 6,
      "독서": 6,
      "산업기반기술": 1,
      "경영·사무관리": 1,
      "외국어": 28,
      "정보": 3,
      "기예(중)": 5,
      "간호보조기술": 1,
      "컴퓨터": 1
    },
    "구례군": {
      "보통교과": 14,
      "예능(중)": 6,
      "간호보조기술": 1,
      "외국어": 1
    },
    "나주시": {
      "외국어": 23,
      "예능(중)": 54,
      "보통교과": 125,
      "산업기반기술": 5,
      "간호보조기술": 2,
      "기예(중)": 13,
      "독서": 3,
      "산업응용기술": 2,
      "기타(중)": 1,
      "문화관광": 1,
      "국제": 1
    },
    "담양군": {
      "보통교과": 10,
      "예능(중)": 6,
      "산업기반기술": 2
    },
    "목포시": {
      "보통교과": 240,
      "외국어": 41,
      "기타(중)": 7,
      "예능(중)": 118,
      "산업응용기술": 8,
      "간호보조기술": 4,
      "독서": 8,
      "인문사회(중)": 4,
      "경영·사무관리": 1,
      "산업기반기술": 1,
      "일반서비스": 1,
      "기예(중)": 5,
      "컴퓨터": 2,
      "산업서비스": 3
    },
    "무안군": {
      "보통교과": 139,
      "외국어": 26,
      "산업기반기술": 1,
      "진학지도": 1,
      "인문사회(중)": 1,
      "예능(중)": 64,
      "기예(중)": 6,
      "기타(중)": 8,
      "독서": 4,
      "산업응용기술": 1,
      "컴퓨터": 1
    },
    "보성군": {
      "보통교과": 18,
      "예능(중)": 8,
      "외국어": 2,
      "기타(중)": 1
    },
    "순천시": {
      "보통교과": 287,
      "예능(중)": 151,
      "외국어": 75,
      "산업응용기술": 12,
      "기타(중)": 18,
      "기예(중)": 9,
      "컴퓨터": 2,
      "독서": 12,
      "산업기반기술": 7,
      "정보": 1,
      "경영·사무관리": 1,
      "일반서비스": 2,
      "인문사회(중)": 2,
      "간호보조기술": 4,
      "산업서비스": 1
    },
    "신안군": {
      "예능(중)": 2,
      "보통교과": 2
    },
    "여수시": {
      "보통교과": 324,
      "컴퓨터": 5,
      "외국어": 51,
      "기타(중)": 18,
      "예능(중)": 150,
      "산업응용기술": 14,
      "독서": 18,
      "간호보조기술": 3,
      "정보": 1,
      "기예(중)": 3,
      "산업서비스": 1,
      "산업기반기술": 1,
      "인문사회(중)": 1,
      "일반서비스": 1,
      "진학지도": 1
    },
    "영광군": {
      "보통교과": 46,
      "독서": 2,
      "예능(중)": 19,
      "외국어": 4,
      "산업응용기술": 1,
      "컴퓨터": 1
    },
    "영암군": {
      "보통교과": 23,
      "예능(중)": 12,
      "외국어": 5,
      "독서": 1,
      "기타(중)": 1,
      "산업응용기술": 1
    },
    "완도군": {
      "외국어": 4,
      "보통교과": 20,
      "산업응용기술": 1,
      "예능(중)": 11,
      "컴퓨터": 1,
      "기예(중)": 1
    },
    "장성군": {
      "보통교과": 22,
      "외국어": 4,
      "예능(중)": 10,
      "인문사회(중)": 1,
      "기타(중)": 1
    },
    "장흥군": {
      "보통교과": 16,
      "외국어": 3,
      "예능(중)": 5,
      "간호보조기술": 1,
      "기타(중)": 1
    },
    "진도군": {
      "보통교과": 19,
      "예능(중)": 7,
      "외국어": 1,
      "독서": 1
    },
    "함평군": {
      "예능(중)": 6,
      "보통교과": 8
    },
    "해남군": {
      "보통교과": 46,
      "예능(중)": 13,
      "기예(중)": 2,
      "컴퓨터": 1,
      "산업응용기술": 3,
      "기타(중)": 1,
      "외국어": 2
    },
    "화순군": {
      "외국어": 2,
      "예능(중)": 17,
      "보통교과": 40,
      "기타(중)": 1,
      "컴퓨터": 1,
      "산업기반기술": 1,
      "독서": 1,
      "간호보조기술": 1
    }
  },
  "경상북도": {
    "경산시": {
      "보통교과": 331,
      "예능(중)": 173,
      "외국어": 48,
      "기타(중)": 10,
      "산업응용기술": 7,
      "산업기반기술": 5,
      "간호보조기술": 4,
      "독서": 15,
      "기예(중)": 1,
      "예능(대)": 1,
      "컴퓨터": 2,
      "국제": 2,
      "정보": 1
    },
    "경주시": {
      "보통교과": 313,
      "기타(중)": 6,
      "예능(중)": 111,
      "간호보조기술": 2,
      "산업기반기술": 6,
      "독서": 8,
      "기예(중)": 5,
      "산업응용기술": 4,
      "외국어": 31,
      "정보": 4,
      "진학지도": 1,
      "일반서비스": 1,
      "컴퓨터": 2,
      "예능(대)": 1
    },
    "고령군": {
      "보통교과": 17,
      "예능(중)": 6,
      "외국어": 1,
      "입시.검정 및 보습": 1
    },
    "구미시": {
      "국제": 4,
      "산업응용기술": 25,
      "외국어": 63,
      "보통교과": 653,
      "예능(중)": 278,
      "기타(중)": 29,
      "기예(중)": 15,
      "간호보조기술": 4,
      "독서": 7,
      "컴퓨터": 4,
      "일반서비스": 3,
      "예능(대)": 1,
      "산업기반기술": 4,
      "경영·사무관리": 1,
      "정보": 2,
      "특수교육(중)": 1,
      "인문사회(중)": 1
    },
    "군위군": {
      "보통교과": 8,
      "예능(중)": 8,
      "기타(중)": 1
    },
    "김천시": {
      "보통교과": 120,
      "외국어": 16,
      "국제": 1,
      "예능(중)": 62,
      "기예(중)": 2,
      "산업서비스": 1,
      "산업기반기술": 1,
      "인문사회(중)": 1,
      "독서": 6,
      "간호보조기술": 1,
      "산업응용기술": 4,
      "일반서비스": 1,
      "기타(중)": 3,
      "정보": 1,
      "입시.검정 및 보습": 1
    },
    "문경시": {
      "보통교과": 52,
      "컴퓨터": 1,
      "산업응용기술": 1,
      "예능(중)": 30,
      "외국어": 7,
      "기타(중)": 1
    },
    "봉화군": {
      "예능(중)": 9,
      "보통교과": 9,
      "기예(중)": 1
    },
    "상주시": {
      "보통교과": 65,
      "예능(중)": 23,
      "외국어": 2,
      "독서": 3,
      "간호보조기술": 1,
      "산업응용기술": 2,
      "산업기반기술": 1
    },
    "성주군": {
      "예능(중)": 8,
      "보통교과": 22,
      "외국어": 5
    },
    "안동시": {
      "보통교과": 190,
      "기예(중)": 3,
      "외국어": 11,
      "예능(중)": 87,
      "산업응용기술": 7,
      "기타(중)": 11,
      "진학지도": 1,
      "독서": 12,
      "경영·사무관리": 1,
      "간호보조기술": 2,
      "인문사회(중)": 1,
      "정보": 1,
      "산업기반기술": 1
    },
    "영덕군": {
      "보통교과": 14,
      "예능(중)": 8,
      "기타(중)": 1,
      "외국어": 2
    },
    "영양군": {
      "예능(중)": 2,
      "보통교과": 2,
      "외국어": 1
    },
    "영주시": {
      "보통교과": 116,
      "산업응용기술": 6,
      "예능(중)": 48,
      "독서": 9,
      "외국어": 9,
      "기예(중)": 2,
      "기타(중)": 3,
      "인문사회(중)": 1,
      "컴퓨터": 2,
      "진학지도": 1,
      "간호보조기술": 1,
      "산업기반기술": 1
    },
    "영천시": {
      "보통교과": 65,
      "외국어": 7,
      "예능(중)": 46,
      "산업응용기술": 3,
      "기예(중)": 2,
      "독서": 3,
      "컴퓨터": 2,
      "간호보조기술": 1,
      "산업기반기술": 1,
      "기타(중)": 1
    },
    "예천군": {
      "보통교과": 49,
      "외국어": 7,
      "예능(중)": 32,
      "간호보조기술": 1,
      "산업응용기술": 2,
      "진학지도": 1,
      "독서": 2,
      "입시.검정 및 보습": 1,
      "기타(중)": 2,
      "경영·사무관리": 1,
      "정보": 1
    },
    "울릉군": {
      "보통교과": 1,
      "예능(중)": 3
    },
    "울진군": {
      "외국어": 9,
      "보통교과": 34,
      "독서": 2,
      "예능(중)": 20,
      "기타(중)": 2,
      "컴퓨터": 1
    },
    "의성군": {
      "보통교과": 9,
      "예능(중)": 8,
      "컴퓨터": 1,
      "산업응용기술": 1
    },
    "청도군": {
      "보통교과": 24,
      "예능(중)": 5,
      "외국어": 1,
      "기예(중)": 1,
      "기타(중)": 1,
      "산업기반기술": 1
    },
    "청송군": {
      "예능(중)": 5,
      "보통교과": 4
    },
    "칠곡군": {
      "외국어": 9,
      "보통교과": 119,
      "예능(중)": 55,
      "산업응용기술": 4,
      "기타(중)": 3,
      "기예(중)": 1,
      "컴퓨터": 1
    },
    "포항시": {
      "기타(중)": 32,
      "외국어": 87,
      "예능(중)": 295,
      "보통교과": 657,
      "컴퓨터": 5,
      "독서": 23,
      "인문사회(중)": 2,
      "간호보조기술": 6,
      "정보": 6,
      "산업응용기술": 17,
      "기예(중)": 12,
      "경영·사무관리": 1,
      "산업기반기술": 4,
      "국제": 2,
      "진학지도": 1,
      "산업서비스": 1,
      "일반서비스": 4
    }
  },
  "경상남도": {
    "거제시": {
      "기타(중)": 15,
      "외국어": 38,
      "보통교과": 240,
      "예능(중)": 146,
      "정보": 1,
      "간호보조기술": 2,
      "산업응용기술": 11,
      "기예(중)": 1,
      "산업기반기술": 6,
      "독서": 6,
      "국제": 1,
      "컴퓨터": 1,
      "입시.검정 및 보습": 1,
      "인문사회(중)": 1
    },
    "거창군": {
      "보통교과": 48,
      "산업기반기술": 1,
      "외국어": 19,
      "산업응용기술": 2,
      "예능(중)": 41,
      "기타(중)": 4,
      "간호보조기술": 1,
      "독서": 4,
      "정보": 1,
      "진학지도": 1,
      "컴퓨터": 1
    },
    "고성군": {
      "예능(중)": 17,
      "보통교과": 52,
      "외국어": 3,
      "독서": 2,
      "기타(중)": 1
    },
    "김해시": {
      "보통교과": 742,
      "산업응용기술": 19,
      "외국어": 106,
      "기예(중)": 10,
      "예능(중)": 357,
      "기타(중)": 22,
      "독서": 12,
      "간호보조기술": 4,
      "산업기반기술": 4,
      "컴퓨터": 2,
      "예능(대)": 1,
      "일반서비스": 2,
      "경영·사무관리": 1,
      "종합(대)": 1,
      "정보": 2,
      "인문사회(중)": 2
    },
    "남해군": {
      "보통교과": 20,
      "예능(중)": 12,
      "독서": 1,
      "외국어": 1
    },
    "밀양시": {
      "보통교과": 116,
      "외국어": 7,
      "기타(중)": 8,
      "예능(중)": 47,
      "산업응용기술": 1,
      "독서": 4,
      "기예(중)": 1,
      "간호보조기술": 1,
      "컴퓨터": 2
    },
    "사천시": {
      "보통교과": 116,
      "예능(중)": 63,
      "정보": 1,
      "산업응용기술": 2,
      "기예(중)": 5,
      "기타(중)": 4,
      "독서": 4,
      "외국어": 8,
      "간호보조기술": 1,
      "컴퓨터": 2
    },
    "산청군": {
      "보통교과": 13,
      "예능(중)": 7,
      "외국어": 3,
      "기타(중)": 2
    },
    "양산시": {
      "보통교과": 481,
      "외국어": 72,
      "예능(중)": 226,
      "산업응용기술": 14,
      "기예(중)": 7,
      "일반서비스": 5,
      "기타(중)": 15,
      "산업기반기술": 2,
      "간호보조기술": 5,
      "컴퓨터": 1,
      "독서": 12,
      "국제": 1,
      "정보": 1,
      "인문사회(중)": 1
    },
    "의령군": {
      "외국어": 3,
      "보통교과": 10,
      "예능(중)": 6
    },
    "진주시": {
      "보통교과": 569,
      "예능(중)": 292,
      "외국어": 106,
      "독서": 24,
      "국제": 4,
      "기타(중)": 20,
      "산업응용기술": 16,
      "기예(중)": 18,
      "진학지도": 2,
      "컴퓨터": 1,
      "정보": 4,
      "산업기반기술": 12,
      "간호보조기술": 2,
      "문화관광": 1,
      "일반서비스": 1,
      "인문사회(중)": 3
    },
    "창녕군": {
      "보통교과": 49,
      "예능(중)": 16,
      "컴퓨터": 1,
      "기예(중)": 1,
      "외국어": 3
    },
    "창원시": {
      "산업기반기술": 18,
      "보통교과": 1504,
      "예능(중)": 695,
      "독서": 41,
      "외국어": 158,
      "기예(중)": 34,
      "인문사회(중)": 11,
      "기타(중)": 42,
      "산업응용기술": 44,
      "국제": 9,
      "정보": 9,
      "경영·사무관리": 5,
      "일반서비스": 6,
      "간호보조기술": 6,
      "산업서비스": 5,
      "예능(대)": 1,
      "컴퓨터": 13,
      "입시.검정 및 보습": 1,
      "문화관광": 1
    },
    "창원시(폐지)": {
      "외국어": 1,
      "보통교과": 1
    },
    "통영시": {
      "입시.검정 및 보습": 1,
      "보통교과": 142,
      "예능(중)": 69,
      "외국어": 17,
      "산업응용기술": 5,
      "산업기반기술": 3,
      "종합(대)": 1,
      "기예(중)": 1,
      "독서": 4,
      "기타(중)": 1,
      "산업서비스": 1,
      "일반서비스": 1,
      "간호보조기술": 1,
      "컴퓨터": 1
    },
    "하동군": {
      "산업응용기술": 2,
      "보통교과": 22,
      "예능(중)": 13,
      "외국어": 2
    },
    "함안군": {
      "산업기반기술": 1,
      "보통교과": 33,
      "외국어": 4,
      "독서": 3,
      "예능(중)": 15
    },
    "함양군": {
      "보통교과": 10,
      "예능(중)": 8,
      "외국어": 7,
      "기예(중)": 1,
      "정보": 1
    },
    "합천군": {
      "보통교과": 19,
      "예능(중)": 9,
      "외국어": 4,
      "입시.검정 및 보습": 1,
      "기타(중)": 1,
      "간호보조기술": 1
    }
  },
  "제주특별자치도": {
    "서귀포시": {
      "보통교과": 170,
      "외국어": 68,
      "예능(중)": 120,
      "기예(중)": 2,
      "산업응용기술": 2,
      "독서": 3,
      "기타(중)": 3,
      "산업기반기술": 3,
      "정보": 4,
      "입시.검정 및 보습": 1,
      "국제": 1,
      "컴퓨터": 1
    },
    "제주시": {
      "보통교과": 651,
      "예능(중)": 295,
      "국제": 3,
      "기예(중)": 13,
      "외국어": 94,
      "산업응용기술": 16,
      "기타(중)": 13,
      "독서": 30,
      "산업기반기술": 4,
      "인문사회(중)": 2,
      "예능(대)": 3,
      "입시.검정 및 보습": 1,
      "간호보조기술": 2,
      "일반서비스": 1,
      "진학지도": 1
    }
  }
}